[
    {
        "timestamp": "2025-04-25T23:00:00.000Z",
        "Station": "Lauwersoog",
        "Weer": "",
        "Temp(\u00b0C)": "8.4",
        "RV(%)": "83",
        "Wind(bft)": "NO 3",
        "Wind(m/s)": "4.1",
        "Windstoot(km/uur)": "18",
        "Zicht(m)": "",
        "Druk(hPa)": ""
    },
    {
        "timestamp": "2025-04-25T23:00:00.000Z",
        "Station": "Nieuw Beerta",
        "Weer": "",
        "Temp(\u00b0C)": "4.9",
        "RV(%)": "93",
        "Wind(bft)": "NO 2",
        "Wind(m/s)": "2.61",
        "Windstoot(km/uur)": "10",
        "Zicht(m)": "",
        "Druk(hPa)": ""
    },
    {
        "timestamp": "2025-04-25T23:00:00.000Z",
        "Station": "Terschelling",
        "Weer": "",
        "Temp(\u00b0C)": "5.3",
        "RV(%)": "93",
        "Wind(bft)": "NNO 2",
        "Wind(m/s)": "1.67",
        "Windstoot(km/uur)": "8",
        "Zicht(m)": "16000",
        "Druk(hPa)": "1024.4"
    },
    {
        "timestamp": "2025-04-25T23:00:00.000Z",
        "Station": "Vlieland",
        "Weer": "geheel bewolkt",
        "Temp(\u00b0C)": "8.2",
        "RV(%)": "86",
        "Wind(bft)": "NO 2",
        "Wind(m/s)": "3.21",
        "Windstoot(km/uur)": "14",
        "Zicht(m)": "24000",
        "Druk(hPa)": "1024.4"
    },
    {
        "timestamp": "2025-04-25T23:00:00.000Z",
        "Station": "Leeuwarden",
        "Weer": "onbewolkt",
        "Temp(\u00b0C)": "4.5",
        "RV(%)": "94",
        "Wind(bft)": "NO 1",
        "Wind(m/s)": "1.09",
        "Windstoot(km/uur)": "6",
        "Zicht(m)": "14000",
        "Druk(hPa)": "1024.2"
    },
    {
        "timestamp": "2025-04-25T23:00:00.000Z",
        "Station": "Stavoren",
        "Weer": "onbewolkt",
        "Temp(\u00b0C)": "7.2",
        "RV(%)": "93",
        "Wind(bft)": "NO 3",
        "Wind(m/s)": "3.48",
        "Windstoot(km/uur)": "17",
        "Zicht(m)": "13000",
        "Druk(hPa)": ""
    },
    {
        "timestamp": "2025-04-25T23:00:00.000Z",
        "Station": "Houtribdijk",
        "Weer": "",
        "Temp(\u00b0C)": "",
        "RV(%)": "",
        "Wind(bft)": "ONO 4",
        "Wind(m/s)": "6.55",
        "Windstoot(km/uur)": "27",
        "Zicht(m)": "",
        "Druk(hPa)": ""
    },
    {
        "timestamp": "2025-04-25T23:00:00.000Z",
        "Station": "Eelde",
        "Weer": "onbewolkt",
        "Temp(\u00b0C)": "4.3",
        "RV(%)": "99",
        "Wind(bft)": "N 1",
        "Wind(m/s)": "1.42",
        "Windstoot(km/uur)": "8",
        "Zicht(m)": "9000",
        "Druk(hPa)": "1024.1"
    },
    {
        "timestamp": "2025-04-25T23:00:00.000Z",
        "Station": "Hoogeveen",
        "Weer": "onbewolkt",
        "Temp(\u00b0C)": "6.2",
        "RV(%)": "97",
        "Wind(bft)": "NNO 2",
        "Wind(m/s)": "1.83",
        "Windstoot(km/uur)": "9",
        "Zicht(m)": "8000",
        "Druk(hPa)": "1023.9"
    },
    {
        "timestamp": "2025-04-25T23:00:00.000Z",
        "Station": "Heino",
        "Weer": "",
        "Temp(\u00b0C)": "7.1",
        "RV(%)": "93",
        "Wind(bft)": "NO 1",
        "Wind(m/s)": "1.21",
        "Windstoot(km/uur)": "8",
        "Zicht(m)": "",
        "Druk(hPa)": ""
    },
    {
        "timestamp": "2025-04-25T23:00:00.000Z",
        "Station": "Twenthe",
        "Weer": "mist",
        "Temp(\u00b0C)": "5.6",
        "RV(%)": "99",
        "Wind(bft)": "NNO 1",
        "Wind(m/s)": "1.01",
        "Windstoot(km/uur)": "5",
        "Zicht(m)": "100",
        "Druk(hPa)": "1023.4"
    },
    {
        "timestamp": "2025-04-25T23:00:00.000Z",
        "Station": "Deelen",
        "Weer": "onbewolkt",
        "Temp(\u00b0C)": "4.3",
        "RV(%)": "94",
        "Wind(bft)": "N 1",
        "Wind(m/s)": "0.61",
        "Windstoot(km/uur)": "3",
        "Zicht(m)": "5000",
        "Druk(hPa)": "1023.4"
    },
    {
        "timestamp": "2025-04-25T23:00:00.000Z",
        "Station": "Hupsel",
        "Weer": "",
        "Temp(\u00b0C)": "4.9",
        "RV(%)": "98",
        "Wind(bft)": "N 1",
        "Wind(m/s)": "1.56",
        "Windstoot(km/uur)": "7",
        "Zicht(m)": "",
        "Druk(hPa)": ""
    },
    {
        "timestamp": "2025-04-25T23:00:00.000Z",
        "Station": "Herwijnen",
        "Weer": "",
        "Temp(\u00b0C)": "6.1",
        "RV(%)": "99",
        "Wind(bft)": "NO 1",
        "Wind(m/s)": "0.72",
        "Windstoot(km/uur)": "3",
        "Zicht(m)": "",
        "Druk(hPa)": "1023.2"
    },
    {
        "timestamp": "2025-04-25T23:00:00.000Z",
        "Station": "Marknesse",
        "Weer": "",
        "Temp(\u00b0C)": "6.4",
        "RV(%)": "97",
        "Wind(bft)": "NNO 2",
        "Wind(m/s)": "1.62",
        "Windstoot(km/uur)": "8",
        "Zicht(m)": "10000",
        "Druk(hPa)": ""
    },
    {
        "timestamp": "2025-04-25T23:00:00.000Z",
        "Station": "Lelystad",
        "Weer": "onbewolkt",
        "Temp(\u00b0C)": "6.4",
        "RV(%)": "96",
        "Wind(bft)": "NO 2",
        "Wind(m/s)": "2.86",
        "Windstoot(km/uur)": "13",
        "Zicht(m)": "10000",
        "Druk(hPa)": "1023.6"
    },
    {
        "timestamp": "2025-04-25T23:00:00.000Z",
        "Station": "De Bilt",
        "Weer": "onbewolkt",
        "Temp(\u00b0C)": "7.2",
        "RV(%)": "97",
        "Wind(bft)": "O 1",
        "Wind(m/s)": "0.8",
        "Windstoot(km/uur)": "4",
        "Zicht(m)": "5000",
        "Druk(hPa)": "1023.2"
    },
    {
        "timestamp": "2025-04-25T23:00:00.000Z",
        "Station": "Cabauw",
        "Weer": "",
        "Temp(\u00b0C)": "8",
        "RV(%)": "92",
        "Wind(bft)": "OZO 1",
        "Wind(m/s)": "0.57",
        "Windstoot(km/uur)": "5",
        "Zicht(m)": "14000",
        "Druk(hPa)": "1023.2"
    },
    {
        "timestamp": "2025-04-25T23:00:00.000Z",
        "Station": "Den Helder",
        "Weer": "onbewolkt",
        "Temp(\u00b0C)": "9",
        "RV(%)": "84",
        "Wind(bft)": "ONO 3",
        "Wind(m/s)": "4.37",
        "Windstoot(km/uur)": "22",
        "Zicht(m)": "23000",
        "Druk(hPa)": "1023.8"
    },
    {
        "timestamp": "2025-04-25T23:00:00.000Z",
        "Station": "Texelhors",
        "Weer": "",
        "Temp(\u00b0C)": "",
        "RV(%)": "",
        "Wind(bft)": "ONO 2",
        "Wind(m/s)": "2.76",
        "Windstoot(km/uur)": "15",
        "Zicht(m)": "",
        "Druk(hPa)": ""
    },
    {
        "timestamp": "2025-04-25T23:00:00.000Z",
        "Station": "Berkhout",
        "Weer": "",
        "Temp(\u00b0C)": "6.3",
        "RV(%)": "96",
        "Wind(bft)": "NO 2",
        "Wind(m/s)": "2.66",
        "Windstoot(km/uur)": "12",
        "Zicht(m)": "10000",
        "Druk(hPa)": ""
    },
    {
        "timestamp": "2025-04-25T23:00:00.000Z",
        "Station": "IJmuiden",
        "Weer": "",
        "Temp(\u00b0C)": "",
        "RV(%)": "",
        "Wind(bft)": "NNO 3",
        "Wind(m/s)": "4.16",
        "Windstoot(km/uur)": "18",
        "Zicht(m)": "",
        "Druk(hPa)": ""
    },
    {
        "timestamp": "2025-04-25T23:00:00.000Z",
        "Station": "Wijk aan Zee",
        "Weer": "",
        "Temp(\u00b0C)": "5.7",
        "RV(%)": "98",
        "Wind(bft)": "",
        "Wind(m/s)": "",
        "Windstoot(km/uur)": "",
        "Zicht(m)": "",
        "Druk(hPa)": ""
    },
    {
        "timestamp": "2025-04-25T23:00:00.000Z",
        "Station": "Schiphol",
        "Weer": "onbewolkt",
        "Temp(\u00b0C)": "8.8",
        "RV(%)": "87",
        "Wind(bft)": "NNO 2",
        "Wind(m/s)": "1.79",
        "Windstoot(km/uur)": "10",
        "Zicht(m)": "30000",
        "Druk(hPa)": "1023.3"
    },
    {
        "timestamp": "2025-04-25T23:00:00.000Z",
        "Station": "Voorschoten",
        "Weer": "onbewolkt",
        "Temp(\u00b0C)": "8.5",
        "RV(%)": "89",
        "Wind(bft)": "O 2",
        "Wind(m/s)": "2.12",
        "Windstoot(km/uur)": "11",
        "Zicht(m)": "26000",
        "Druk(hPa)": "1023.4"
    },
    {
        "timestamp": "2025-04-25T23:00:00.000Z",
        "Station": "Rotterdam",
        "Weer": "onbewolkt",
        "Temp(\u00b0C)": "8.2",
        "RV(%)": "86",
        "Wind(bft)": "O 2",
        "Wind(m/s)": "1.6",
        "Windstoot(km/uur)": "9",
        "Zicht(m)": "19000",
        "Druk(hPa)": "1023.2"
    },
    {
        "timestamp": "2025-04-25T23:00:00.000Z",
        "Station": "Hoek van Holland",
        "Weer": "",
        "Temp(\u00b0C)": "8.4",
        "RV(%)": "93",
        "Wind(bft)": "NO 3",
        "Wind(m/s)": "4.31",
        "Windstoot(km/uur)": "18",
        "Zicht(m)": "",
        "Druk(hPa)": "1023.2"
    },
    {
        "timestamp": "2025-04-25T23:00:00.000Z",
        "Station": "Wilhelminadorp",
        "Weer": "",
        "Temp(\u00b0C)": "10.4",
        "RV(%)": "82",
        "Wind(bft)": "O 2",
        "Wind(m/s)": "2.82",
        "Windstoot(km/uur)": "15",
        "Zicht(m)": "",
        "Druk(hPa)": "1022.8"
    },
    {
        "timestamp": "2025-04-25T23:00:00.000Z",
        "Station": "Vlissingen",
        "Weer": "licht bewolkt",
        "Temp(\u00b0C)": "9.9",
        "RV(%)": "89",
        "Wind(bft)": "NNO 3",
        "Wind(m/s)": "4.39",
        "Windstoot(km/uur)": "21",
        "Zicht(m)": "14000",
        "Druk(hPa)": "1022.6"
    },
    {
        "timestamp": "2025-04-25T23:00:00.000Z",
        "Station": "Westdorpe",
        "Weer": "",
        "Temp(\u00b0C)": "10.5",
        "RV(%)": "84",
        "Wind(bft)": "OZO 2",
        "Wind(m/s)": "2.08",
        "Windstoot(km/uur)": "12",
        "Zicht(m)": "14000",
        "Druk(hPa)": "1022.8"
    },
    {
        "timestamp": "2025-04-25T23:00:00.000Z",
        "Station": "Woensdrecht",
        "Weer": "onbewolkt",
        "Temp(\u00b0C)": "8.7",
        "RV(%)": "86",
        "Wind(bft)": "O 1",
        "Wind(m/s)": "1.52",
        "Windstoot(km/uur)": "9",
        "Zicht(m)": "10000",
        "Druk(hPa)": "1022.9"
    },
    {
        "timestamp": "2025-04-25T23:00:00.000Z",
        "Station": "Gilze Rijen",
        "Weer": "onbewolkt",
        "Temp(\u00b0C)": "6.7",
        "RV(%)": "93",
        "Wind(bft)": "NO 1",
        "Wind(m/s)": "0.8",
        "Windstoot(km/uur)": "4",
        "Zicht(m)": "11000",
        "Druk(hPa)": "1023.1"
    },
    {
        "timestamp": "2025-04-25T23:00:00.000Z",
        "Station": "Volkel",
        "Weer": "onbewolkt",
        "Temp(\u00b0C)": "5",
        "RV(%)": "98",
        "Wind(bft)": "N 1",
        "Wind(m/s)": "1.23",
        "Windstoot(km/uur)": "7",
        "Zicht(m)": "4000",
        "Druk(hPa)": "1023.2"
    },
    {
        "timestamp": "2025-04-25T23:00:00.000Z",
        "Station": "Eindhoven",
        "Weer": "onbewolkt",
        "Temp(\u00b0C)": "5.3",
        "RV(%)": "99",
        "Wind(bft)": "N 1",
        "Wind(m/s)": "0.94",
        "Windstoot(km/uur)": "4",
        "Zicht(m)": "7000",
        "Druk(hPa)": "1023.0"
    },
    {
        "timestamp": "2025-04-25T23:00:00.000Z",
        "Station": "Ell",
        "Weer": "onbewolkt",
        "Temp(\u00b0C)": "7.4",
        "RV(%)": "95",
        "Wind(bft)": "N 2",
        "Wind(m/s)": "1.87",
        "Windstoot(km/uur)": "9",
        "Zicht(m)": "8000",
        "Druk(hPa)": ""
    },
    {
        "timestamp": "2025-04-25T23:00:00.000Z",
        "Station": "Arcen",
        "Weer": "",
        "Temp(\u00b0C)": "6.5",
        "RV(%)": "95",
        "Wind(bft)": "N 1",
        "Wind(m/s)": "1.11",
        "Windstoot(km/uur)": "6",
        "Zicht(m)": "",
        "Druk(hPa)": ""
    },
    {
        "timestamp": "2025-04-25T23:00:00.000Z",
        "Station": "Maastricht-Aachen Airport",
        "Weer": "onbewolkt",
        "Temp(\u00b0C)": "7.4",
        "RV(%)": "94",
        "Wind(bft)": "N 2",
        "Wind(m/s)": "2.49",
        "Windstoot(km/uur)": "11",
        "Zicht(m)": "9000",
        "Druk(hPa)": "1022.5"
    }
]
