[
    {
        "timestamp": "2025-04-01T18:00:00.000Z",
        "Station": "Lauwersoog",
        "Weer": "",
        "Temp(\u00b0C)": "10.8",
        "RV(%)": "71",
        "Wind(bft)": "ONO 5",
        "Wind(m/s)": "9.67",
        "Windstoot(km/uur)": "40",
        "Zicht(m)": "",
        "Druk(hPa)": ""
    },
    {
        "timestamp": "2025-04-01T18:00:00.000Z",
        "Station": "Nieuw Beerta",
        "Weer": "",
        "Temp(\u00b0C)": "13.5",
        "RV(%)": "47",
        "Wind(bft)": "ONO 4",
        "Wind(m/s)": "5.61",
        "Windstoot(km/uur)": "28",
        "Zicht(m)": "",
        "Druk(hPa)": ""
    },
    {
        "timestamp": "2025-04-01T18:00:00.000Z",
        "Station": "Terschelling",
        "Weer": "",
        "Temp(\u00b0C)": "9.7",
        "RV(%)": "66",
        "Wind(bft)": "ONO 5",
        "Wind(m/s)": "8.88",
        "Windstoot(km/uur)": "43",
        "Zicht(m)": "35000",
        "Druk(hPa)": "1028.9"
    },
    {
        "timestamp": "2025-04-01T18:00:00.000Z",
        "Station": "Vlieland",
        "Weer": "onbewolkt",
        "Temp(\u00b0C)": "11.2",
        "RV(%)": "60",
        "Wind(bft)": "ONO 5",
        "Wind(m/s)": "10.62",
        "Windstoot(km/uur)": "48",
        "Zicht(m)": "35000",
        "Druk(hPa)": "1028.0"
    },
    {
        "timestamp": "2025-04-01T18:00:00.000Z",
        "Station": "Leeuwarden",
        "Weer": "onbewolkt",
        "Temp(\u00b0C)": "12.2",
        "RV(%)": "59",
        "Wind(bft)": "ONO 4",
        "Wind(m/s)": "7.56",
        "Windstoot(km/uur)": "37",
        "Zicht(m)": "34000",
        "Druk(hPa)": "1028.2"
    },
    {
        "timestamp": "2025-04-01T18:00:00.000Z",
        "Station": "Stavoren",
        "Weer": "onbewolkt",
        "Temp(\u00b0C)": "14",
        "RV(%)": "40",
        "Wind(bft)": "O 4",
        "Wind(m/s)": "6.47",
        "Windstoot(km/uur)": "36",
        "Zicht(m)": "40000",
        "Druk(hPa)": ""
    },
    {
        "timestamp": "2025-04-01T18:00:00.000Z",
        "Station": "Houtribdijk",
        "Weer": "",
        "Temp(\u00b0C)": "",
        "RV(%)": "",
        "Wind(bft)": "OZO 4",
        "Wind(m/s)": "7.11",
        "Windstoot(km/uur)": "31",
        "Zicht(m)": "",
        "Druk(hPa)": ""
    },
    {
        "timestamp": "2025-04-01T18:00:00.000Z",
        "Station": "Eelde",
        "Weer": "onbewolkt",
        "Temp(\u00b0C)": "14",
        "RV(%)": "40",
        "Wind(bft)": "ONO 4",
        "Wind(m/s)": "6.29",
        "Windstoot(km/uur)": "32",
        "Zicht(m)": "35000",
        "Druk(hPa)": "1028.2"
    },
    {
        "timestamp": "2025-04-01T18:00:00.000Z",
        "Station": "Hoogeveen",
        "Weer": "onbewolkt",
        "Temp(\u00b0C)": "13.7",
        "RV(%)": "42",
        "Wind(bft)": "O 4",
        "Wind(m/s)": "6.49",
        "Windstoot(km/uur)": "35",
        "Zicht(m)": "50000",
        "Druk(hPa)": "1027.7"
    },
    {
        "timestamp": "2025-04-01T18:00:00.000Z",
        "Station": "Heino",
        "Weer": "",
        "Temp(\u00b0C)": "13.6",
        "RV(%)": "41",
        "Wind(bft)": "O 4",
        "Wind(m/s)": "6.2",
        "Windstoot(km/uur)": "33",
        "Zicht(m)": "",
        "Druk(hPa)": ""
    },
    {
        "timestamp": "2025-04-01T18:00:00.000Z",
        "Station": "Twenthe",
        "Weer": "onbewolkt",
        "Temp(\u00b0C)": "13.8",
        "RV(%)": "41",
        "Wind(bft)": "O 3",
        "Wind(m/s)": "5.32",
        "Windstoot(km/uur)": "30",
        "Zicht(m)": "40000",
        "Druk(hPa)": "1027.2"
    },
    {
        "timestamp": "2025-04-01T18:00:00.000Z",
        "Station": "Deelen",
        "Weer": "onbewolkt",
        "Temp(\u00b0C)": "13.9",
        "RV(%)": "39",
        "Wind(bft)": "ONO 4",
        "Wind(m/s)": "5.58",
        "Windstoot(km/uur)": "35",
        "Zicht(m)": "45000",
        "Druk(hPa)": "1026.3"
    },
    {
        "timestamp": "2025-04-01T18:00:00.000Z",
        "Station": "Hupsel",
        "Weer": "",
        "Temp(\u00b0C)": "13",
        "RV(%)": "46",
        "Wind(bft)": "O 4",
        "Wind(m/s)": "6.49",
        "Windstoot(km/uur)": "37",
        "Zicht(m)": "",
        "Druk(hPa)": ""
    },
    {
        "timestamp": "2025-04-01T18:00:00.000Z",
        "Station": "Herwijnen",
        "Weer": "",
        "Temp(\u00b0C)": "13.6",
        "RV(%)": "43",
        "Wind(bft)": "O 5",
        "Wind(m/s)": "8.78",
        "Windstoot(km/uur)": "43",
        "Zicht(m)": "",
        "Druk(hPa)": "1025.7"
    },
    {
        "timestamp": "2025-04-01T18:00:00.000Z",
        "Station": "Marknesse",
        "Weer": "",
        "Temp(\u00b0C)": "14.5",
        "RV(%)": "38",
        "Wind(bft)": "O 4",
        "Wind(m/s)": "7.65",
        "Windstoot(km/uur)": "39",
        "Zicht(m)": "50000",
        "Druk(hPa)": ""
    },
    {
        "timestamp": "2025-04-01T18:00:00.000Z",
        "Station": "Lelystad",
        "Weer": "onbewolkt",
        "Temp(\u00b0C)": "14.1",
        "RV(%)": "38",
        "Wind(bft)": "O 4",
        "Wind(m/s)": "6.27",
        "Windstoot(km/uur)": "39",
        "Zicht(m)": "35000",
        "Druk(hPa)": "1026.6"
    },
    {
        "timestamp": "2025-04-01T18:00:00.000Z",
        "Station": "De Bilt",
        "Weer": "onbewolkt",
        "Temp(\u00b0C)": "13.8",
        "RV(%)": "38",
        "Wind(bft)": "ONO 4",
        "Wind(m/s)": "7.4",
        "Windstoot(km/uur)": "39",
        "Zicht(m)": "40000",
        "Druk(hPa)": "1026.1"
    },
    {
        "timestamp": "2025-04-01T18:00:00.000Z",
        "Station": "Cabauw",
        "Weer": "",
        "Temp(\u00b0C)": "13.8",
        "RV(%)": "40",
        "Wind(bft)": "O 4",
        "Wind(m/s)": "6.76",
        "Windstoot(km/uur)": "39",
        "Zicht(m)": "45000",
        "Druk(hPa)": "1025.7"
    },
    {
        "timestamp": "2025-04-01T18:00:00.000Z",
        "Station": "Den Helder",
        "Weer": "onbewolkt",
        "Temp(\u00b0C)": "13.2",
        "RV(%)": "52",
        "Wind(bft)": "ONO 4",
        "Wind(m/s)": "6.22",
        "Windstoot(km/uur)": "30",
        "Zicht(m)": "45000",
        "Druk(hPa)": "1027.4"
    },
    {
        "timestamp": "2025-04-01T18:00:00.000Z",
        "Station": "Texelhors",
        "Weer": "",
        "Temp(\u00b0C)": "",
        "RV(%)": "",
        "Wind(bft)": "ONO 4",
        "Wind(m/s)": "7.83",
        "Windstoot(km/uur)": "38",
        "Zicht(m)": "",
        "Druk(hPa)": ""
    },
    {
        "timestamp": "2025-04-01T18:00:00.000Z",
        "Station": "Berkhout",
        "Weer": "",
        "Temp(\u00b0C)": "13.5",
        "RV(%)": "44",
        "Wind(bft)": "O 4",
        "Wind(m/s)": "6.93",
        "Windstoot(km/uur)": "35",
        "Zicht(m)": "40000",
        "Druk(hPa)": ""
    },
    {
        "timestamp": "2025-04-01T18:00:00.000Z",
        "Station": "IJmuiden",
        "Weer": "",
        "Temp(\u00b0C)": "",
        "RV(%)": "",
        "Wind(bft)": "ONO 5",
        "Wind(m/s)": "9.3",
        "Windstoot(km/uur)": "48",
        "Zicht(m)": "",
        "Druk(hPa)": ""
    },
    {
        "timestamp": "2025-04-01T18:00:00.000Z",
        "Station": "Wijk aan Zee",
        "Weer": "",
        "Temp(\u00b0C)": "13.9",
        "RV(%)": "39",
        "Wind(bft)": "",
        "Wind(m/s)": "",
        "Windstoot(km/uur)": "",
        "Zicht(m)": "",
        "Druk(hPa)": ""
    },
    {
        "timestamp": "2025-04-01T18:00:00.000Z",
        "Station": "Schiphol",
        "Weer": "onbewolkt",
        "Temp(\u00b0C)": "13.9",
        "RV(%)": "42",
        "Wind(bft)": "O 4",
        "Wind(m/s)": "5.96",
        "Windstoot(km/uur)": "41",
        "Zicht(m)": "40000",
        "Druk(hPa)": "1026.2"
    },
    {
        "timestamp": "2025-04-01T18:00:00.000Z",
        "Station": "Voorschoten",
        "Weer": "onbewolkt",
        "Temp(\u00b0C)": "13.5",
        "RV(%)": "45",
        "Wind(bft)": "O 4",
        "Wind(m/s)": "7.69",
        "Windstoot(km/uur)": "37",
        "Zicht(m)": "35000",
        "Druk(hPa)": "1025.8"
    },
    {
        "timestamp": "2025-04-01T18:00:00.000Z",
        "Station": "Rotterdam",
        "Weer": "onbewolkt",
        "Temp(\u00b0C)": "13.5",
        "RV(%)": "43",
        "Wind(bft)": "O 4",
        "Wind(m/s)": "7.63",
        "Windstoot(km/uur)": "41",
        "Zicht(m)": "31000",
        "Druk(hPa)": "1025.5"
    },
    {
        "timestamp": "2025-04-01T18:00:00.000Z",
        "Station": "Hoek van Holland",
        "Weer": "",
        "Temp(\u00b0C)": "13.9",
        "RV(%)": "40",
        "Wind(bft)": "O 5",
        "Wind(m/s)": "9.69",
        "Windstoot(km/uur)": "46",
        "Zicht(m)": "",
        "Druk(hPa)": "1025.5"
    },
    {
        "timestamp": "2025-04-01T18:00:00.000Z",
        "Station": "Wilhelminadorp",
        "Weer": "",
        "Temp(\u00b0C)": "13.1",
        "RV(%)": "52",
        "Wind(bft)": "ONO 4",
        "Wind(m/s)": "7.17",
        "Windstoot(km/uur)": "43",
        "Zicht(m)": "",
        "Druk(hPa)": "1024.4"
    },
    {
        "timestamp": "2025-04-01T18:00:00.000Z",
        "Station": "Vlissingen",
        "Weer": "onbewolkt",
        "Temp(\u00b0C)": "13.4",
        "RV(%)": "46",
        "Wind(bft)": "ONO 5",
        "Wind(m/s)": "8.14",
        "Windstoot(km/uur)": "42",
        "Zicht(m)": "35000",
        "Druk(hPa)": "1024.1"
    },
    {
        "timestamp": "2025-04-01T18:00:00.000Z",
        "Station": "Westdorpe",
        "Weer": "",
        "Temp(\u00b0C)": "14.3",
        "RV(%)": "35",
        "Wind(bft)": "O 4",
        "Wind(m/s)": "7.4",
        "Windstoot(km/uur)": "44",
        "Zicht(m)": "50000",
        "Druk(hPa)": "1023.7"
    },
    {
        "timestamp": "2025-04-01T18:00:00.000Z",
        "Station": "Woensdrecht",
        "Weer": "onbewolkt",
        "Temp(\u00b0C)": "14.1",
        "RV(%)": "40",
        "Wind(bft)": "ONO 5",
        "Wind(m/s)": "9.05",
        "Windstoot(km/uur)": "48",
        "Zicht(m)": "40000",
        "Druk(hPa)": "1024.3"
    },
    {
        "timestamp": "2025-04-01T18:00:00.000Z",
        "Station": "Gilze Rijen",
        "Weer": "licht bewolkt",
        "Temp(\u00b0C)": "13.7",
        "RV(%)": "39",
        "Wind(bft)": "ONO 4",
        "Wind(m/s)": "7.19",
        "Windstoot(km/uur)": "44",
        "Zicht(m)": "45000",
        "Druk(hPa)": "1025.1"
    },
    {
        "timestamp": "2025-04-01T18:00:00.000Z",
        "Station": "Volkel",
        "Weer": "licht bewolkt",
        "Temp(\u00b0C)": "13.8",
        "RV(%)": "44",
        "Wind(bft)": "ONO 5",
        "Wind(m/s)": "9.28",
        "Windstoot(km/uur)": "48",
        "Zicht(m)": "40000",
        "Druk(hPa)": "1025.5"
    },
    {
        "timestamp": "2025-04-01T18:00:00.000Z",
        "Station": "Eindhoven",
        "Weer": "licht bewolkt",
        "Temp(\u00b0C)": "14.3",
        "RV(%)": "38",
        "Wind(bft)": "O 4",
        "Wind(m/s)": "6.22",
        "Windstoot(km/uur)": "40",
        "Zicht(m)": "40000",
        "Druk(hPa)": "1025.0"
    },
    {
        "timestamp": "2025-04-01T18:00:00.000Z",
        "Station": "Ell",
        "Weer": "half bewolkt",
        "Temp(\u00b0C)": "13.5",
        "RV(%)": "42",
        "Wind(bft)": "ONO 4",
        "Wind(m/s)": "6.76",
        "Windstoot(km/uur)": "39",
        "Zicht(m)": "50000",
        "Druk(hPa)": ""
    },
    {
        "timestamp": "2025-04-01T18:00:00.000Z",
        "Station": "Arcen",
        "Weer": "",
        "Temp(\u00b0C)": "13.9",
        "RV(%)": "39",
        "Wind(bft)": "O 4",
        "Wind(m/s)": "5.69",
        "Windstoot(km/uur)": "39",
        "Zicht(m)": "",
        "Druk(hPa)": ""
    },
    {
        "timestamp": "2025-04-01T18:00:00.000Z",
        "Station": "Maastricht-Aachen Airport",
        "Weer": "onbewolkt",
        "Temp(\u00b0C)": "13.2",
        "RV(%)": "39",
        "Wind(bft)": "O 5",
        "Wind(m/s)": "8.95",
        "Windstoot(km/uur)": "46",
        "Zicht(m)": "40000",
        "Druk(hPa)": "1024.2"
    }
]
