[
    {
        "timestamp": "2025-12-25T12:40:00.000Z",
        "Station": "Lauwersoog",
        "Weer": "",
        "Temp(\u00b0C)": "0.1",
        "Chill(\u00b0C)": "-7.0",
        "RV(%)": "64",
        "Wind(bft)": "ONO 5",
        "Wind(m/s)": "10.16",
        "Windstoot(km/uur)": "45",
        "Zicht(m)": "",
        "Druk(hPa)": ""
    },
    {
        "timestamp": "2025-12-25T12:40:00.000Z",
        "Station": "Nieuw Beerta",
        "Weer": "",
        "Temp(\u00b0C)": "-1.7",
        "Chill(\u00b0C)": "-8.0",
        "RV(%)": "64",
        "Wind(bft)": "ONO 4",
        "Wind(m/s)": "6.78",
        "Windstoot(km/uur)": "35",
        "Zicht(m)": "",
        "Druk(hPa)": ""
    },
    {
        "timestamp": "2025-12-25T12:40:00.000Z",
        "Station": "Terschelling",
        "Weer": "",
        "Temp(\u00b0C)": "1.2",
        "Chill(\u00b0C)": "-5.3",
        "RV(%)": "50",
        "Wind(bft)": "ONO 5",
        "Wind(m/s)": "9.36",
        "Windstoot(km/uur)": "44",
        "Zicht(m)": "35000",
        "Druk(hPa)": "1035.3"
    },
    {
        "timestamp": "2025-12-25T12:40:00.000Z",
        "Station": "Vlieland",
        "Weer": "onbewolkt",
        "Temp(\u00b0C)": "1.2",
        "Chill(\u00b0C)": "-5.7",
        "RV(%)": "57",
        "Wind(bft)": "ONO 6",
        "Wind(m/s)": "10.89",
        "Windstoot(km/uur)": "49",
        "Zicht(m)": "45000",
        "Druk(hPa)": "1034.7"
    },
    {
        "timestamp": "2025-12-25T12:40:00.000Z",
        "Station": "Leeuwarden",
        "Weer": "onbewolkt",
        "Temp(\u00b0C)": "-0.6",
        "Chill(\u00b0C)": "-6.8",
        "RV(%)": "56",
        "Wind(bft)": "ONO 4",
        "Wind(m/s)": "7.32",
        "Windstoot(km/uur)": "37",
        "Zicht(m)": "45000",
        "Druk(hPa)": "1035.1"
    },
    {
        "timestamp": "2025-12-25T12:40:00.000Z",
        "Station": "Stavoren",
        "Weer": "onbewolkt",
        "Temp(\u00b0C)": "-0.6",
        "Chill(\u00b0C)": "-6.6",
        "RV(%)": "54",
        "Wind(bft)": "ONO 4",
        "Wind(m/s)": "6.84",
        "Windstoot(km/uur)": "36",
        "Zicht(m)": "45000",
        "Druk(hPa)": ""
    },
    {
        "timestamp": "2025-12-25T12:40:00.000Z",
        "Station": "Houtribdijk",
        "Weer": "",
        "Temp(\u00b0C)": "",
        "Chill(\u00b0C)": "",
        "RV(%)": "",
        "Wind(bft)": "O 6",
        "Wind(m/s)": "12.43",
        "Windstoot(km/uur)": "53",
        "Zicht(m)": "",
        "Druk(hPa)": ""
    },
    {
        "timestamp": "2025-12-25T12:40:00.000Z",
        "Station": "Eelde",
        "Weer": "onbewolkt",
        "Temp(\u00b0C)": "-1.5",
        "Chill(\u00b0C)": "-7.7",
        "RV(%)": "61",
        "Wind(bft)": "NO 4",
        "Wind(m/s)": "6.7",
        "Windstoot(km/uur)": "35",
        "Zicht(m)": "45000",
        "Druk(hPa)": "1035.2"
    },
    {
        "timestamp": "2025-12-25T12:40:00.000Z",
        "Station": "Hoogeveen",
        "Weer": "onbewolkt",
        "Temp(\u00b0C)": "-2.2",
        "Chill(\u00b0C)": "-8.0",
        "RV(%)": "60",
        "Wind(bft)": "ONO 4",
        "Wind(m/s)": "5.61",
        "Windstoot(km/uur)": "34",
        "Zicht(m)": "50000",
        "Druk(hPa)": "1034.2"
    },
    {
        "timestamp": "2025-12-25T12:40:00.000Z",
        "Station": "Heino",
        "Weer": "",
        "Temp(\u00b0C)": "-2.1",
        "Chill(\u00b0C)": "-8.3",
        "RV(%)": "60",
        "Wind(bft)": "ONO 4",
        "Wind(m/s)": "6.24",
        "Windstoot(km/uur)": "35",
        "Zicht(m)": "",
        "Druk(hPa)": ""
    },
    {
        "timestamp": "2025-12-25T12:40:00.000Z",
        "Station": "Twenthe",
        "Weer": "onbewolkt",
        "Temp(\u00b0C)": "-2.8",
        "Chill(\u00b0C)": "-8.5",
        "RV(%)": "66",
        "Wind(bft)": "ONO 3",
        "Wind(m/s)": "5.17",
        "Windstoot(km/uur)": "29",
        "Zicht(m)": "34000",
        "Druk(hPa)": "1032.5"
    },
    {
        "timestamp": "2025-12-25T12:40:00.000Z",
        "Station": "Deelen",
        "Weer": "onbewolkt",
        "Temp(\u00b0C)": "-2",
        "Chill(\u00b0C)": "-8.0",
        "RV(%)": "64",
        "Wind(bft)": "ONO 4",
        "Wind(m/s)": "6.06",
        "Windstoot(km/uur)": "33",
        "Zicht(m)": "40000",
        "Druk(hPa)": "1031.1"
    },
    {
        "timestamp": "2025-12-25T12:40:00.000Z",
        "Station": "Hupsel",
        "Weer": "",
        "Temp(\u00b0C)": "-2.1",
        "Chill(\u00b0C)": "-7.8",
        "RV(%)": "65",
        "Wind(bft)": "ONO 3",
        "Wind(m/s)": "5.38",
        "Windstoot(km/uur)": "29",
        "Zicht(m)": "",
        "Druk(hPa)": ""
    },
    {
        "timestamp": "2025-12-25T12:40:00.000Z",
        "Station": "Herwijnen",
        "Weer": "",
        "Temp(\u00b0C)": "-1.1",
        "Chill(\u00b0C)": "-7.7",
        "RV(%)": "66",
        "Wind(bft)": "ONO 4",
        "Wind(m/s)": "7.85",
        "Windstoot(km/uur)": "42",
        "Zicht(m)": "",
        "Druk(hPa)": "1030.2"
    },
    {
        "timestamp": "2025-12-25T12:40:00.000Z",
        "Station": "Marknesse",
        "Weer": "",
        "Temp(\u00b0C)": "-1.8",
        "Chill(\u00b0C)": "-8.8",
        "RV(%)": "64",
        "Wind(bft)": "ONO 5",
        "Wind(m/s)": "8.25",
        "Windstoot(km/uur)": "41",
        "Zicht(m)": "50000",
        "Druk(hPa)": ""
    },
    {
        "timestamp": "2025-12-25T12:40:00.000Z",
        "Station": "Lelystad",
        "Weer": "onbewolkt",
        "Temp(\u00b0C)": "-1.7",
        "Chill(\u00b0C)": "-8.6",
        "RV(%)": "63",
        "Wind(bft)": "ONO 5",
        "Wind(m/s)": "8.12",
        "Windstoot(km/uur)": "39",
        "Zicht(m)": "45000",
        "Druk(hPa)": "1032.3"
    },
    {
        "timestamp": "2025-12-25T12:40:00.000Z",
        "Station": "De Bilt",
        "Weer": "onbewolkt",
        "Temp(\u00b0C)": "-1.4",
        "Chill(\u00b0C)": "-7.7",
        "RV(%)": "62",
        "Wind(bft)": "ONO 4",
        "Wind(m/s)": "6.88",
        "Windstoot(km/uur)": "43",
        "Zicht(m)": "35000",
        "Druk(hPa)": "1030.8"
    },
    {
        "timestamp": "2025-12-25T12:40:00.000Z",
        "Station": "Cabauw",
        "Weer": "",
        "Temp(\u00b0C)": "-1.3",
        "Chill(\u00b0C)": "-7.5",
        "RV(%)": "63",
        "Wind(bft)": "ONO 4",
        "Wind(m/s)": "6.87",
        "Windstoot(km/uur)": "36",
        "Zicht(m)": "35000",
        "Druk(hPa)": "1030.4"
    },
    {
        "timestamp": "2025-12-25T12:40:00.000Z",
        "Station": "Den Helder",
        "Weer": "onbewolkt",
        "Temp(\u00b0C)": "0.5",
        "Chill(\u00b0C)": "-6.3",
        "RV(%)": "54",
        "Wind(bft)": "ONO 5",
        "Wind(m/s)": "9.71",
        "Windstoot(km/uur)": "45",
        "Zicht(m)": "40000",
        "Druk(hPa)": "1033.6"
    },
    {
        "timestamp": "2025-12-25T12:40:00.000Z",
        "Station": "Texelhors",
        "Weer": "",
        "Temp(\u00b0C)": "",
        "Chill(\u00b0C)": "",
        "RV(%)": "",
        "Wind(bft)": "ONO 5",
        "Wind(m/s)": "8.66",
        "Windstoot(km/uur)": "44",
        "Zicht(m)": "",
        "Druk(hPa)": ""
    },
    {
        "timestamp": "2025-12-25T12:40:00.000Z",
        "Station": "Berkhout",
        "Weer": "",
        "Temp(\u00b0C)": "-0.5",
        "Chill(\u00b0C)": "-6.8",
        "RV(%)": "59",
        "Wind(bft)": "ONO 4",
        "Wind(m/s)": "7.54",
        "Windstoot(km/uur)": "40",
        "Zicht(m)": "31000",
        "Druk(hPa)": ""
    },
    {
        "timestamp": "2025-12-25T12:40:00.000Z",
        "Station": "IJmuiden",
        "Weer": "",
        "Temp(\u00b0C)": "",
        "Chill(\u00b0C)": "",
        "RV(%)": "",
        "Wind(bft)": "ONO 6",
        "Wind(m/s)": "13.57",
        "Windstoot(km/uur)": "61",
        "Zicht(m)": "",
        "Druk(hPa)": ""
    },
    {
        "timestamp": "2025-12-25T12:40:00.000Z",
        "Station": "Wijk aan Zee",
        "Weer": "",
        "Temp(\u00b0C)": "-0.7",
        "Chill(\u00b0C)": "",
        "RV(%)": "60",
        "Wind(bft)": "",
        "Wind(m/s)": "",
        "Windstoot(km/uur)": "",
        "Zicht(m)": "",
        "Druk(hPa)": ""
    },
    {
        "timestamp": "2025-12-25T12:40:00.000Z",
        "Station": "Schiphol",
        "Weer": "onbewolkt",
        "Temp(\u00b0C)": "-1.3",
        "Chill(\u00b0C)": "-8.5",
        "RV(%)": "59",
        "Wind(bft)": "ONO 5",
        "Wind(m/s)": "9.34",
        "Windstoot(km/uur)": "44",
        "Zicht(m)": "30000",
        "Druk(hPa)": "1031.3"
    },
    {
        "timestamp": "2025-12-25T12:40:00.000Z",
        "Station": "Voorschoten",
        "Weer": "onbewolkt",
        "Temp(\u00b0C)": "-1.4",
        "Chill(\u00b0C)": "-8.0",
        "RV(%)": "63",
        "Wind(bft)": "ONO 4",
        "Wind(m/s)": "7.69",
        "Windstoot(km/uur)": "47",
        "Zicht(m)": "45000",
        "Druk(hPa)": "1030.6"
    },
    {
        "timestamp": "2025-12-25T12:40:00.000Z",
        "Station": "Rotterdam",
        "Weer": "onbewolkt",
        "Temp(\u00b0C)": "-1",
        "Chill(\u00b0C)": "-7.8",
        "RV(%)": "62",
        "Wind(bft)": "O 5",
        "Wind(m/s)": "8.29",
        "Windstoot(km/uur)": "47",
        "Zicht(m)": "45000",
        "Druk(hPa)": "1030.2"
    },
    {
        "timestamp": "2025-12-25T12:40:00.000Z",
        "Station": "Hoek van Holland",
        "Weer": "",
        "Temp(\u00b0C)": "-1",
        "Chill(\u00b0C)": "-8.6",
        "RV(%)": "61",
        "Wind(bft)": "O 6",
        "Wind(m/s)": "10.8",
        "Windstoot(km/uur)": "54",
        "Zicht(m)": "",
        "Druk(hPa)": "1030.2"
    },
    {
        "timestamp": "2025-12-25T12:40:00.000Z",
        "Station": "Wilhelminadorp",
        "Weer": "",
        "Temp(\u00b0C)": "-1.6",
        "Chill(\u00b0C)": "-8.6",
        "RV(%)": "67",
        "Wind(bft)": "O 5",
        "Wind(m/s)": "8.55",
        "Windstoot(km/uur)": "49",
        "Zicht(m)": "",
        "Druk(hPa)": "1028.9"
    },
    {
        "timestamp": "2025-12-25T12:40:00.000Z",
        "Station": "Vlissingen",
        "Weer": "onbewolkt",
        "Temp(\u00b0C)": "-1.3",
        "Chill(\u00b0C)": "-8.8",
        "RV(%)": "69",
        "Wind(bft)": "ONO 5",
        "Wind(m/s)": "10",
        "Windstoot(km/uur)": "48",
        "Zicht(m)": "40000",
        "Druk(hPa)": "1028.5"
    },
    {
        "timestamp": "2025-12-25T12:40:00.000Z",
        "Station": "Westdorpe",
        "Weer": "",
        "Temp(\u00b0C)": "-1.4",
        "Chill(\u00b0C)": "-8.0",
        "RV(%)": "66",
        "Wind(bft)": "ONO 4",
        "Wind(m/s)": "7.67",
        "Windstoot(km/uur)": "39",
        "Zicht(m)": "50000",
        "Druk(hPa)": "1028.6"
    },
    {
        "timestamp": "2025-12-25T12:40:00.000Z",
        "Station": "Woensdrecht",
        "Weer": "onbewolkt",
        "Temp(\u00b0C)": "-1.8",
        "Chill(\u00b0C)": "-8.5",
        "RV(%)": "65",
        "Wind(bft)": "ONO 4",
        "Wind(m/s)": "7.52",
        "Windstoot(km/uur)": "41",
        "Zicht(m)": "40000",
        "Druk(hPa)": "1028.7"
    },
    {
        "timestamp": "2025-12-25T12:40:00.000Z",
        "Station": "Gilze Rijen",
        "Weer": "onbewolkt",
        "Temp(\u00b0C)": "-1.8",
        "Chill(\u00b0C)": "-8.2",
        "RV(%)": "66",
        "Wind(bft)": "ONO 4",
        "Wind(m/s)": "6.86",
        "Windstoot(km/uur)": "35",
        "Zicht(m)": "45000",
        "Druk(hPa)": "1029.6"
    },
    {
        "timestamp": "2025-12-25T12:40:00.000Z",
        "Station": "Volkel",
        "Weer": "onbewolkt",
        "Temp(\u00b0C)": "-1.5",
        "Chill(\u00b0C)": "-7.6",
        "RV(%)": "63",
        "Wind(bft)": "NO 4",
        "Wind(m/s)": "6.51",
        "Windstoot(km/uur)": "33",
        "Zicht(m)": "29000",
        "Druk(hPa)": "1030.2"
    },
    {
        "timestamp": "2025-12-25T12:40:00.000Z",
        "Station": "Eindhoven",
        "Weer": "onbewolkt",
        "Temp(\u00b0C)": "-1.4",
        "Chill(\u00b0C)": "-7.2",
        "RV(%)": "62",
        "Wind(bft)": "ONO 4",
        "Wind(m/s)": "6",
        "Windstoot(km/uur)": "30",
        "Zicht(m)": "35000",
        "Druk(hPa)": "1029.5"
    },
    {
        "timestamp": "2025-12-25T12:40:00.000Z",
        "Station": "Ell",
        "Weer": "licht bewolkt",
        "Temp(\u00b0C)": "-2",
        "Chill(\u00b0C)": "-8.1",
        "RV(%)": "66",
        "Wind(bft)": "NO 4",
        "Wind(m/s)": "6.1",
        "Windstoot(km/uur)": "32",
        "Zicht(m)": "50000",
        "Druk(hPa)": ""
    },
    {
        "timestamp": "2025-12-25T12:40:00.000Z",
        "Station": "Horst",
        "Weer": "",
        "Temp(\u00b0C)": "-1.4",
        "Chill(\u00b0C)": "-6.6",
        "RV(%)": "67",
        "Wind(bft)": "ONO 3",
        "Wind(m/s)": "4.84",
        "Windstoot(km/uur)": "31",
        "Zicht(m)": "",
        "Druk(hPa)": ""
    },
    {
        "timestamp": "2025-12-25T12:40:00.000Z",
        "Station": "Maastricht-Aachen Airport",
        "Weer": "geheel bewolkt",
        "Temp(\u00b0C)": "-0.8",
        "Chill(\u00b0C)": "-6.9",
        "RV(%)": "66",
        "Wind(bft)": "ONO 4",
        "Wind(m/s)": "6.9",
        "Windstoot(km/uur)": "33",
        "Zicht(m)": "35000",
        "Druk(hPa)": "1028.0"
    }
]
