[
    {
        "timestamp": "2025-03-16T17:20:00.000Z",
        "Station": "Lauwersoog",
        "Weer": "",
        "Temp(\u00b0C)": "6.2",
        "Chill(\u00b0C)": "2.0",
        "RV(%)": "90",
        "Wind(bft)": "WNW 4",
        "Wind(m/s)": "7.03",
        "Windstoot(km/uur)": "30",
        "Zicht(m)": "",
        "Druk(hPa)": ""
    },
    {
        "timestamp": "2025-03-16T17:20:00.000Z",
        "Station": "Nieuw Beerta",
        "Weer": "",
        "Temp(\u00b0C)": "6.3",
        "Chill(\u00b0C)": "2.9",
        "RV(%)": "86",
        "Wind(bft)": "WNW 3",
        "Wind(m/s)": "5.09",
        "Windstoot(km/uur)": "25",
        "Zicht(m)": "",
        "Druk(hPa)": ""
    },
    {
        "timestamp": "2025-03-16T17:20:00.000Z",
        "Station": "Terschelling",
        "Weer": "af en toe lichte regen",
        "Temp(\u00b0C)": "6.2",
        "Chill(\u00b0C)": "3.5",
        "RV(%)": "96",
        "Wind(bft)": "NW 3",
        "Wind(m/s)": "3.71",
        "Windstoot(km/uur)": "20",
        "Zicht(m)": "18000",
        "Druk(hPa)": "1023.4"
    },
    {
        "timestamp": "2025-03-16T17:20:00.000Z",
        "Station": "Vlieland",
        "Weer": "droog na regen",
        "Temp(\u00b0C)": "6.3",
        "Chill(\u00b0C)": "2.7",
        "RV(%)": "91",
        "Wind(bft)": "WNW 4",
        "Wind(m/s)": "5.54",
        "Windstoot(km/uur)": "25",
        "Zicht(m)": "26000",
        "Druk(hPa)": "1023.6"
    },
    {
        "timestamp": "2025-03-16T17:20:00.000Z",
        "Station": "Leeuwarden",
        "Weer": "geheel bewolkt",
        "Temp(\u00b0C)": "6.4",
        "Chill(\u00b0C)": "2.8",
        "RV(%)": "85",
        "Wind(bft)": "NW 4",
        "Wind(m/s)": "5.61",
        "Windstoot(km/uur)": "25",
        "Zicht(m)": "40000",
        "Druk(hPa)": "1023.1"
    },
    {
        "timestamp": "2025-03-16T17:20:00.000Z",
        "Station": "Stavoren",
        "Weer": "geheel bewolkt",
        "Temp(\u00b0C)": "6.9",
        "Chill(\u00b0C)": "3.6",
        "RV(%)": "78",
        "Wind(bft)": "NNW 3",
        "Wind(m/s)": "5.17",
        "Windstoot(km/uur)": "25",
        "Zicht(m)": "40000",
        "Druk(hPa)": ""
    },
    {
        "timestamp": "2025-03-16T17:20:00.000Z",
        "Station": "Houtribdijk",
        "Weer": "",
        "Temp(\u00b0C)": "",
        "Chill(\u00b0C)": "",
        "RV(%)": "",
        "Wind(bft)": "NNW 4",
        "Wind(m/s)": "7.21",
        "Windstoot(km/uur)": "29",
        "Zicht(m)": "",
        "Druk(hPa)": ""
    },
    {
        "timestamp": "2025-03-16T17:20:00.000Z",
        "Station": "Eelde",
        "Weer": "droog na regen",
        "Temp(\u00b0C)": "6",
        "Chill(\u00b0C)": "2.5",
        "RV(%)": "87",
        "Wind(bft)": "NW 3",
        "Wind(m/s)": "5.15",
        "Windstoot(km/uur)": "25",
        "Zicht(m)": "45000",
        "Druk(hPa)": "1022.6"
    },
    {
        "timestamp": "2025-03-16T17:20:00.000Z",
        "Station": "Hoogeveen",
        "Weer": "zwaar bewolkt",
        "Temp(\u00b0C)": "7.2",
        "Chill(\u00b0C)": "4.5",
        "RV(%)": "66",
        "Wind(bft)": "NNW 3",
        "Wind(m/s)": "4.14",
        "Windstoot(km/uur)": "22",
        "Zicht(m)": "50000",
        "Druk(hPa)": "1022.4"
    },
    {
        "timestamp": "2025-03-16T17:20:00.000Z",
        "Station": "Heino",
        "Weer": "",
        "Temp(\u00b0C)": "7.6",
        "Chill(\u00b0C)": "6.6",
        "RV(%)": "62",
        "Wind(bft)": "NNW 2",
        "Wind(m/s)": "1.81",
        "Windstoot(km/uur)": "16",
        "Zicht(m)": "",
        "Druk(hPa)": ""
    },
    {
        "timestamp": "2025-03-16T17:20:00.000Z",
        "Station": "Twenthe",
        "Weer": "geheel bewolkt",
        "Temp(\u00b0C)": "7.3",
        "Chill(\u00b0C)": "4.8",
        "RV(%)": "57",
        "Wind(bft)": "NNO 3",
        "Wind(m/s)": "3.67",
        "Windstoot(km/uur)": "20",
        "Zicht(m)": "45000",
        "Druk(hPa)": "1022.2"
    },
    {
        "timestamp": "2025-03-16T17:20:00.000Z",
        "Station": "Deelen",
        "Weer": "half bewolkt",
        "Temp(\u00b0C)": "8.3",
        "Chill(\u00b0C)": "5.4",
        "RV(%)": "52",
        "Wind(bft)": "N 3",
        "Wind(m/s)": "5.15",
        "Windstoot(km/uur)": "29",
        "Zicht(m)": "45000",
        "Druk(hPa)": "1022.5"
    },
    {
        "timestamp": "2025-03-16T17:20:00.000Z",
        "Station": "Hupsel",
        "Weer": "",
        "Temp(\u00b0C)": "7.4",
        "Chill(\u00b0C)": "4.1",
        "RV(%)": "57",
        "Wind(bft)": "N 4",
        "Wind(m/s)": "5.56",
        "Windstoot(km/uur)": "28",
        "Zicht(m)": "",
        "Druk(hPa)": ""
    },
    {
        "timestamp": "2025-03-16T17:20:00.000Z",
        "Station": "Herwijnen",
        "Weer": "",
        "Temp(\u00b0C)": "7.9",
        "Chill(\u00b0C)": "4.6",
        "RV(%)": "56",
        "Wind(bft)": "N 4",
        "Wind(m/s)": "5.94",
        "Windstoot(km/uur)": "32",
        "Zicht(m)": "",
        "Druk(hPa)": "1022.5"
    },
    {
        "timestamp": "2025-03-16T17:20:00.000Z",
        "Station": "Marknesse",
        "Weer": "",
        "Temp(\u00b0C)": "7.8",
        "Chill(\u00b0C)": "5.1",
        "RV(%)": "65",
        "Wind(bft)": "N 3",
        "Wind(m/s)": "4.33",
        "Windstoot(km/uur)": "25",
        "Zicht(m)": "50000",
        "Druk(hPa)": ""
    },
    {
        "timestamp": "2025-03-16T17:20:00.000Z",
        "Station": "Lelystad",
        "Weer": "geheel bewolkt",
        "Temp(\u00b0C)": "6.9",
        "Chill(\u00b0C)": "4.8",
        "RV(%)": "72",
        "Wind(bft)": "NW 2",
        "Wind(m/s)": "2.94",
        "Windstoot(km/uur)": "22",
        "Zicht(m)": "40000",
        "Druk(hPa)": "1023.0"
    },
    {
        "timestamp": "2025-03-16T17:20:00.000Z",
        "Station": "De Bilt",
        "Weer": "onbewolkt",
        "Temp(\u00b0C)": "7.4",
        "Chill(\u00b0C)": "4.1",
        "RV(%)": "56",
        "Wind(bft)": "NNO 4",
        "Wind(m/s)": "5.58",
        "Windstoot(km/uur)": "30",
        "Zicht(m)": "45000",
        "Druk(hPa)": "1023.0"
    },
    {
        "timestamp": "2025-03-16T17:20:00.000Z",
        "Station": "Cabauw",
        "Weer": "",
        "Temp(\u00b0C)": "7.3",
        "Chill(\u00b0C)": "3.6",
        "RV(%)": "61",
        "Wind(bft)": "N 4",
        "Wind(m/s)": "6.43",
        "Windstoot(km/uur)": "35",
        "Zicht(m)": "45000",
        "Druk(hPa)": "1022.9"
    },
    {
        "timestamp": "2025-03-16T17:20:00.000Z",
        "Station": "Den Helder",
        "Weer": "geheel bewolkt",
        "Temp(\u00b0C)": "6.6",
        "Chill(\u00b0C)": "3.5",
        "RV(%)": "76",
        "Wind(bft)": "NW 3",
        "Wind(m/s)": "4.66",
        "Windstoot(km/uur)": "24",
        "Zicht(m)": "45000",
        "Druk(hPa)": "1023.8"
    },
    {
        "timestamp": "2025-03-16T17:20:00.000Z",
        "Station": "Texelhors",
        "Weer": "",
        "Temp(\u00b0C)": "",
        "Chill(\u00b0C)": "",
        "RV(%)": "",
        "Wind(bft)": "NNW 4",
        "Wind(m/s)": "6.57",
        "Windstoot(km/uur)": "28",
        "Zicht(m)": "",
        "Druk(hPa)": ""
    },
    {
        "timestamp": "2025-03-16T17:20:00.000Z",
        "Station": "Berkhout",
        "Weer": "",
        "Temp(\u00b0C)": "7.2",
        "Chill(\u00b0C)": "4.1",
        "RV(%)": "69",
        "Wind(bft)": "N 3",
        "Wind(m/s)": "4.95",
        "Windstoot(km/uur)": "22",
        "Zicht(m)": "28000",
        "Druk(hPa)": ""
    },
    {
        "timestamp": "2025-03-16T17:20:00.000Z",
        "Station": "IJmuiden",
        "Weer": "",
        "Temp(\u00b0C)": "",
        "Chill(\u00b0C)": "",
        "RV(%)": "",
        "Wind(bft)": "N 4",
        "Wind(m/s)": "5.91",
        "Windstoot(km/uur)": "27",
        "Zicht(m)": "",
        "Druk(hPa)": ""
    },
    {
        "timestamp": "2025-03-16T17:20:00.000Z",
        "Station": "Wijk aan Zee",
        "Weer": "",
        "Temp(\u00b0C)": "6.7",
        "Chill(\u00b0C)": "",
        "RV(%)": "72",
        "Wind(bft)": "",
        "Wind(m/s)": "",
        "Windstoot(km/uur)": "",
        "Zicht(m)": "",
        "Druk(hPa)": ""
    },
    {
        "timestamp": "2025-03-16T17:20:00.000Z",
        "Station": "Schiphol",
        "Weer": "geheel bewolkt",
        "Temp(\u00b0C)": "7.1",
        "Chill(\u00b0C)": "3.5",
        "RV(%)": "63",
        "Wind(bft)": "N 4",
        "Wind(m/s)": "6.02",
        "Windstoot(km/uur)": "29",
        "Zicht(m)": "45000",
        "Druk(hPa)": "1023.3"
    },
    {
        "timestamp": "2025-03-16T17:20:00.000Z",
        "Station": "Voorschoten",
        "Weer": "zwaar bewolkt",
        "Temp(\u00b0C)": "6.9",
        "Chill(\u00b0C)": "3.0",
        "RV(%)": "68",
        "Wind(bft)": "N 4",
        "Wind(m/s)": "6.86",
        "Windstoot(km/uur)": "33",
        "Zicht(m)": "40000",
        "Druk(hPa)": "1023.5"
    },
    {
        "timestamp": "2025-03-16T17:20:00.000Z",
        "Station": "Rotterdam",
        "Weer": "half bewolkt",
        "Temp(\u00b0C)": "7.9",
        "Chill(\u00b0C)": "5.0",
        "RV(%)": "61",
        "Wind(bft)": "N 3",
        "Wind(m/s)": "4.92",
        "Windstoot(km/uur)": "30",
        "Zicht(m)": "45000",
        "Druk(hPa)": "1023.1"
    },
    {
        "timestamp": "2025-03-16T17:20:00.000Z",
        "Station": "Hoek van Holland",
        "Weer": "",
        "Temp(\u00b0C)": "6.9",
        "Chill(\u00b0C)": "2.0",
        "RV(%)": "64",
        "Wind(bft)": "N 5",
        "Wind(m/s)": "10.27",
        "Windstoot(km/uur)": "42",
        "Zicht(m)": "",
        "Druk(hPa)": "1023.6"
    },
    {
        "timestamp": "2025-03-16T17:20:00.000Z",
        "Station": "Wilhelminadorp",
        "Weer": "",
        "Temp(\u00b0C)": "7.2",
        "Chill(\u00b0C)": "4.0",
        "RV(%)": "63",
        "Wind(bft)": "N 3",
        "Wind(m/s)": "5.25",
        "Windstoot(km/uur)": "32",
        "Zicht(m)": "",
        "Druk(hPa)": "1023.1"
    },
    {
        "timestamp": "2025-03-16T17:20:00.000Z",
        "Station": "Vlissingen",
        "Weer": "onbewolkt",
        "Temp(\u00b0C)": "6.9",
        "Chill(\u00b0C)": "2.8",
        "RV(%)": "63",
        "Wind(bft)": "N 4",
        "Wind(m/s)": "7.36",
        "Windstoot(km/uur)": "35",
        "Zicht(m)": "40000",
        "Druk(hPa)": "1023.1"
    },
    {
        "timestamp": "2025-03-16T17:20:00.000Z",
        "Station": "Westdorpe",
        "Weer": "",
        "Temp(\u00b0C)": "7.9",
        "Chill(\u00b0C)": "4.5",
        "RV(%)": "59",
        "Wind(bft)": "N 4",
        "Wind(m/s)": "6.22",
        "Windstoot(km/uur)": "32",
        "Zicht(m)": "50000",
        "Druk(hPa)": "1022.9"
    },
    {
        "timestamp": "2025-03-16T17:20:00.000Z",
        "Station": "Woensdrecht",
        "Weer": "onbewolkt",
        "Temp(\u00b0C)": "8.1",
        "Chill(\u00b0C)": "5.0",
        "RV(%)": "40",
        "Wind(bft)": "NO 4",
        "Wind(m/s)": "5.56",
        "Windstoot(km/uur)": "29",
        "Zicht(m)": "45000",
        "Druk(hPa)": "1022.7"
    },
    {
        "timestamp": "2025-03-16T17:20:00.000Z",
        "Station": "Gilze Rijen",
        "Weer": "onbewolkt",
        "Temp(\u00b0C)": "8.2",
        "Chill(\u00b0C)": "5.0",
        "RV(%)": "50",
        "Wind(bft)": "N 4",
        "Wind(m/s)": "5.87",
        "Windstoot(km/uur)": "30",
        "Zicht(m)": "40000",
        "Druk(hPa)": "1022.3"
    },
    {
        "timestamp": "2025-03-16T17:20:00.000Z",
        "Station": "Volkel",
        "Weer": "onbewolkt",
        "Temp(\u00b0C)": "8.8",
        "Chill(\u00b0C)": "6.5",
        "RV(%)": "44",
        "Wind(bft)": "NO 3",
        "Wind(m/s)": "4.04",
        "Windstoot(km/uur)": "24",
        "Zicht(m)": "40000",
        "Druk(hPa)": "1022.0"
    },
    {
        "timestamp": "2025-03-16T17:20:00.000Z",
        "Station": "Eindhoven",
        "Weer": "onbewolkt",
        "Temp(\u00b0C)": "9.1",
        "Chill(\u00b0C)": "6.3",
        "RV(%)": "41",
        "Wind(bft)": "N 3",
        "Wind(m/s)": "5.42",
        "Windstoot(km/uur)": "28",
        "Zicht(m)": "45000",
        "Druk(hPa)": "1022.0"
    },
    {
        "timestamp": "2025-03-16T17:20:00.000Z",
        "Station": "Ell",
        "Weer": "onbewolkt",
        "Temp(\u00b0C)": "8.9",
        "Chill(\u00b0C)": "6.6",
        "RV(%)": "43",
        "Wind(bft)": "NNO 3",
        "Wind(m/s)": "4.06",
        "Windstoot(km/uur)": "24",
        "Zicht(m)": "50000",
        "Druk(hPa)": ""
    },
    {
        "timestamp": "2025-03-16T17:20:00.000Z",
        "Station": "Arcen",
        "Weer": "",
        "Temp(\u00b0C)": "8.6",
        "Chill(\u00b0C)": "6.3",
        "RV(%)": "34",
        "Wind(bft)": "NNO 3",
        "Wind(m/s)": "3.98",
        "Windstoot(km/uur)": "25",
        "Zicht(m)": "",
        "Druk(hPa)": ""
    },
    {
        "timestamp": "2025-03-16T17:20:00.000Z",
        "Station": "Maastricht-Aachen Airport",
        "Weer": "onbewolkt",
        "Temp(\u00b0C)": "8.4",
        "Chill(\u00b0C)": "5.6",
        "RV(%)": "47",
        "Wind(bft)": "NNO 3",
        "Wind(m/s)": "4.82",
        "Windstoot(km/uur)": "29",
        "Zicht(m)": "40000",
        "Druk(hPa)": "1021.3"
    }
]
