[
    {
        "timestamp": "2025-04-01T19:40:00.000Z",
        "Station": "Lauwersoog",
        "Weer": "",
        "Temp(\u00b0C)": "9.7",
        "RV(%)": "75",
        "Wind(bft)": "NO 5",
        "Wind(m/s)": "9.32",
        "Windstoot(km/uur)": "39",
        "Zicht(m)": "",
        "Druk(hPa)": ""
    },
    {
        "timestamp": "2025-04-01T19:40:00.000Z",
        "Station": "Nieuw Beerta",
        "Weer": "",
        "Temp(\u00b0C)": "10.2",
        "RV(%)": "65",
        "Wind(bft)": "NO 3",
        "Wind(m/s)": "4.53",
        "Windstoot(km/uur)": "25",
        "Zicht(m)": "",
        "Druk(hPa)": ""
    },
    {
        "timestamp": "2025-04-01T19:40:00.000Z",
        "Station": "Terschelling",
        "Weer": "",
        "Temp(\u00b0C)": "8.1",
        "RV(%)": "74",
        "Wind(bft)": "ONO 5",
        "Wind(m/s)": "8.53",
        "Windstoot(km/uur)": "39",
        "Zicht(m)": "35000",
        "Druk(hPa)": "1028.6"
    },
    {
        "timestamp": "2025-04-01T19:40:00.000Z",
        "Station": "Vlieland",
        "Weer": "onbewolkt",
        "Temp(\u00b0C)": "9.4",
        "RV(%)": "68",
        "Wind(bft)": "ONO 5",
        "Wind(m/s)": "8.93",
        "Windstoot(km/uur)": "43",
        "Zicht(m)": "45000",
        "Druk(hPa)": "1028.0"
    },
    {
        "timestamp": "2025-04-01T19:40:00.000Z",
        "Station": "Leeuwarden",
        "Weer": "onbewolkt",
        "Temp(\u00b0C)": "9.9",
        "RV(%)": "71",
        "Wind(bft)": "NO 4",
        "Wind(m/s)": "5.77",
        "Windstoot(km/uur)": "31",
        "Zicht(m)": "40000",
        "Druk(hPa)": "1028.3"
    },
    {
        "timestamp": "2025-04-01T19:40:00.000Z",
        "Station": "Stavoren",
        "Weer": "onbewolkt",
        "Temp(\u00b0C)": "11.3",
        "RV(%)": "51",
        "Wind(bft)": "O 3",
        "Wind(m/s)": "4.76",
        "Windstoot(km/uur)": "24",
        "Zicht(m)": "45000",
        "Druk(hPa)": ""
    },
    {
        "timestamp": "2025-04-01T19:40:00.000Z",
        "Station": "Houtribdijk",
        "Weer": "",
        "Temp(\u00b0C)": "",
        "RV(%)": "",
        "Wind(bft)": "O 5",
        "Wind(m/s)": "8.99",
        "Windstoot(km/uur)": "38",
        "Zicht(m)": "",
        "Druk(hPa)": ""
    },
    {
        "timestamp": "2025-04-01T19:40:00.000Z",
        "Station": "Eelde",
        "Weer": "onbewolkt",
        "Temp(\u00b0C)": "11.7",
        "RV(%)": "55",
        "Wind(bft)": "ONO 3",
        "Wind(m/s)": "5.07",
        "Windstoot(km/uur)": "29",
        "Zicht(m)": "40000",
        "Druk(hPa)": "1028.3"
    },
    {
        "timestamp": "2025-04-01T19:40:00.000Z",
        "Station": "Hoogeveen",
        "Weer": "onbewolkt",
        "Temp(\u00b0C)": "12.2",
        "RV(%)": "45",
        "Wind(bft)": "O 3",
        "Wind(m/s)": "4.68",
        "Windstoot(km/uur)": "28",
        "Zicht(m)": "50000",
        "Druk(hPa)": "1027.7"
    },
    {
        "timestamp": "2025-04-01T19:40:00.000Z",
        "Station": "Heino",
        "Weer": "",
        "Temp(\u00b0C)": "11.3",
        "RV(%)": "50",
        "Wind(bft)": "O 3",
        "Wind(m/s)": "4.08",
        "Windstoot(km/uur)": "25",
        "Zicht(m)": "",
        "Druk(hPa)": ""
    },
    {
        "timestamp": "2025-04-01T19:40:00.000Z",
        "Station": "Twenthe",
        "Weer": "onbewolkt",
        "Temp(\u00b0C)": "12.3",
        "RV(%)": "44",
        "Wind(bft)": "O 3",
        "Wind(m/s)": "3.67",
        "Windstoot(km/uur)": "25",
        "Zicht(m)": "45000",
        "Druk(hPa)": "1027.2"
    },
    {
        "timestamp": "2025-04-01T19:40:00.000Z",
        "Station": "Deelen",
        "Weer": "onbewolkt",
        "Temp(\u00b0C)": "12.5",
        "RV(%)": "43",
        "Wind(bft)": "O 3",
        "Wind(m/s)": "4.53",
        "Windstoot(km/uur)": "28",
        "Zicht(m)": "45000",
        "Druk(hPa)": "1026.4"
    },
    {
        "timestamp": "2025-04-01T19:40:00.000Z",
        "Station": "Hupsel",
        "Weer": "",
        "Temp(\u00b0C)": "11.5",
        "RV(%)": "49",
        "Wind(bft)": "O 3",
        "Wind(m/s)": "4.18",
        "Windstoot(km/uur)": "25",
        "Zicht(m)": "",
        "Druk(hPa)": ""
    },
    {
        "timestamp": "2025-04-01T19:40:00.000Z",
        "Station": "Herwijnen",
        "Weer": "",
        "Temp(\u00b0C)": "12.2",
        "RV(%)": "48",
        "Wind(bft)": "O 4",
        "Wind(m/s)": "5.81",
        "Windstoot(km/uur)": "31",
        "Zicht(m)": "",
        "Druk(hPa)": "1025.5"
    },
    {
        "timestamp": "2025-04-01T19:40:00.000Z",
        "Station": "Marknesse",
        "Weer": "",
        "Temp(\u00b0C)": "12.7",
        "RV(%)": "45",
        "Wind(bft)": "O 4",
        "Wind(m/s)": "5.65",
        "Windstoot(km/uur)": "28",
        "Zicht(m)": "50000",
        "Druk(hPa)": ""
    },
    {
        "timestamp": "2025-04-01T19:40:00.000Z",
        "Station": "Lelystad",
        "Weer": "onbewolkt",
        "Temp(\u00b0C)": "12.7",
        "RV(%)": "43",
        "Wind(bft)": "O 3",
        "Wind(m/s)": "5.28",
        "Windstoot(km/uur)": "29",
        "Zicht(m)": "45000",
        "Druk(hPa)": "1026.7"
    },
    {
        "timestamp": "2025-04-01T19:40:00.000Z",
        "Station": "De Bilt",
        "Weer": "onbewolkt",
        "Temp(\u00b0C)": "12.7",
        "RV(%)": "43",
        "Wind(bft)": "O 3",
        "Wind(m/s)": "4.8",
        "Windstoot(km/uur)": "32",
        "Zicht(m)": "45000",
        "Druk(hPa)": "1026.0"
    },
    {
        "timestamp": "2025-04-01T19:40:00.000Z",
        "Station": "Cabauw",
        "Weer": "",
        "Temp(\u00b0C)": "12.9",
        "RV(%)": "44",
        "Wind(bft)": "O 4",
        "Wind(m/s)": "6.02",
        "Windstoot(km/uur)": "33",
        "Zicht(m)": "45000",
        "Druk(hPa)": "1025.6"
    },
    {
        "timestamp": "2025-04-01T19:40:00.000Z",
        "Station": "Den Helder",
        "Weer": "onbewolkt",
        "Temp(\u00b0C)": "10.7",
        "RV(%)": "76",
        "Wind(bft)": "NO 5",
        "Wind(m/s)": "8.74",
        "Windstoot(km/uur)": "40",
        "Zicht(m)": "35000",
        "Druk(hPa)": "1027.3"
    },
    {
        "timestamp": "2025-04-01T19:40:00.000Z",
        "Station": "Texelhors",
        "Weer": "",
        "Temp(\u00b0C)": "",
        "RV(%)": "",
        "Wind(bft)": "NO 5",
        "Wind(m/s)": "8.04",
        "Windstoot(km/uur)": "41",
        "Zicht(m)": "",
        "Druk(hPa)": ""
    },
    {
        "timestamp": "2025-04-01T19:40:00.000Z",
        "Station": "Berkhout",
        "Weer": "",
        "Temp(\u00b0C)": "12.1",
        "RV(%)": "49",
        "Wind(bft)": "O 4",
        "Wind(m/s)": "6.24",
        "Windstoot(km/uur)": "34",
        "Zicht(m)": "45000",
        "Druk(hPa)": ""
    },
    {
        "timestamp": "2025-04-01T19:40:00.000Z",
        "Station": "IJmuiden",
        "Weer": "",
        "Temp(\u00b0C)": "",
        "RV(%)": "",
        "Wind(bft)": "O 4",
        "Wind(m/s)": "7.3",
        "Windstoot(km/uur)": "39",
        "Zicht(m)": "",
        "Druk(hPa)": ""
    },
    {
        "timestamp": "2025-04-01T19:40:00.000Z",
        "Station": "Wijk aan Zee",
        "Weer": "",
        "Temp(\u00b0C)": "12.6",
        "RV(%)": "43",
        "Wind(bft)": "",
        "Wind(m/s)": "",
        "Windstoot(km/uur)": "",
        "Zicht(m)": "",
        "Druk(hPa)": ""
    },
    {
        "timestamp": "2025-04-01T19:40:00.000Z",
        "Station": "Schiphol",
        "Weer": "onbewolkt",
        "Temp(\u00b0C)": "12.5",
        "RV(%)": "43",
        "Wind(bft)": "O 4",
        "Wind(m/s)": "6.55",
        "Windstoot(km/uur)": "34",
        "Zicht(m)": "45000",
        "Druk(hPa)": "1026.1"
    },
    {
        "timestamp": "2025-04-01T19:40:00.000Z",
        "Station": "Voorschoten",
        "Weer": "onbewolkt",
        "Temp(\u00b0C)": "12.7",
        "RV(%)": "43",
        "Wind(bft)": "O 3",
        "Wind(m/s)": "5.42",
        "Windstoot(km/uur)": "33",
        "Zicht(m)": "45000",
        "Druk(hPa)": "1025.7"
    },
    {
        "timestamp": "2025-04-01T19:40:00.000Z",
        "Station": "Rotterdam",
        "Weer": "onbewolkt",
        "Temp(\u00b0C)": "12.8",
        "RV(%)": "42",
        "Wind(bft)": "O 4",
        "Wind(m/s)": "6.66",
        "Windstoot(km/uur)": "36",
        "Zicht(m)": "35000",
        "Druk(hPa)": "1025.3"
    },
    {
        "timestamp": "2025-04-01T19:40:00.000Z",
        "Station": "Hoek van Holland",
        "Weer": "",
        "Temp(\u00b0C)": "13.2",
        "RV(%)": "39",
        "Wind(bft)": "O 5",
        "Wind(m/s)": "8.53",
        "Windstoot(km/uur)": "41",
        "Zicht(m)": "",
        "Druk(hPa)": "1025.3"
    },
    {
        "timestamp": "2025-04-01T19:40:00.000Z",
        "Station": "Wilhelminadorp",
        "Weer": "",
        "Temp(\u00b0C)": "12.3",
        "RV(%)": "46",
        "Wind(bft)": "O 4",
        "Wind(m/s)": "6.7",
        "Windstoot(km/uur)": "33",
        "Zicht(m)": "",
        "Druk(hPa)": "1024.3"
    },
    {
        "timestamp": "2025-04-01T19:40:00.000Z",
        "Station": "Vlissingen",
        "Weer": "onbewolkt",
        "Temp(\u00b0C)": "12.7",
        "RV(%)": "46",
        "Wind(bft)": "ONO 5",
        "Wind(m/s)": "8.04",
        "Windstoot(km/uur)": "42",
        "Zicht(m)": "45000",
        "Druk(hPa)": "1024.0"
    },
    {
        "timestamp": "2025-04-01T19:40:00.000Z",
        "Station": "Westdorpe",
        "Weer": "",
        "Temp(\u00b0C)": "13.1",
        "RV(%)": "40",
        "Wind(bft)": "O 4",
        "Wind(m/s)": "5.52",
        "Windstoot(km/uur)": "36",
        "Zicht(m)": "50000",
        "Druk(hPa)": "1023.8"
    },
    {
        "timestamp": "2025-04-01T19:40:00.000Z",
        "Station": "Woensdrecht",
        "Weer": "onbewolkt",
        "Temp(\u00b0C)": "12.8",
        "RV(%)": "43",
        "Wind(bft)": "O 4",
        "Wind(m/s)": "6.14",
        "Windstoot(km/uur)": "38",
        "Zicht(m)": "45000",
        "Druk(hPa)": "1024.3"
    },
    {
        "timestamp": "2025-04-01T19:40:00.000Z",
        "Station": "Gilze Rijen",
        "Weer": "onbewolkt",
        "Temp(\u00b0C)": "12.5",
        "RV(%)": "41",
        "Wind(bft)": "O 4",
        "Wind(m/s)": "7.32",
        "Windstoot(km/uur)": "39",
        "Zicht(m)": "45000",
        "Druk(hPa)": "1024.9"
    },
    {
        "timestamp": "2025-04-01T19:40:00.000Z",
        "Station": "Volkel",
        "Weer": "onbewolkt",
        "Temp(\u00b0C)": "12.4",
        "RV(%)": "45",
        "Wind(bft)": "O 4",
        "Wind(m/s)": "5.98",
        "Windstoot(km/uur)": "35",
        "Zicht(m)": "40000",
        "Druk(hPa)": "1025.5"
    },
    {
        "timestamp": "2025-04-01T19:40:00.000Z",
        "Station": "Eindhoven",
        "Weer": "onbewolkt",
        "Temp(\u00b0C)": "13.2",
        "RV(%)": "42",
        "Wind(bft)": "ONO 4",
        "Wind(m/s)": "5.63",
        "Windstoot(km/uur)": "39",
        "Zicht(m)": "45000",
        "Druk(hPa)": "1025.0"
    },
    {
        "timestamp": "2025-04-01T19:40:00.000Z",
        "Station": "Ell",
        "Weer": "onbewolkt",
        "Temp(\u00b0C)": "12.4",
        "RV(%)": "42",
        "Wind(bft)": "O 3",
        "Wind(m/s)": "4.95",
        "Windstoot(km/uur)": "28",
        "Zicht(m)": "50000",
        "Druk(hPa)": ""
    },
    {
        "timestamp": "2025-04-01T19:40:00.000Z",
        "Station": "Arcen",
        "Weer": "",
        "Temp(\u00b0C)": "12.7",
        "RV(%)": "41",
        "Wind(bft)": "ONO 3",
        "Wind(m/s)": "4.31",
        "Windstoot(km/uur)": "26",
        "Zicht(m)": "",
        "Druk(hPa)": ""
    },
    {
        "timestamp": "2025-04-01T19:40:00.000Z",
        "Station": "Maastricht-Aachen Airport",
        "Weer": "onbewolkt",
        "Temp(\u00b0C)": "11.8",
        "RV(%)": "42",
        "Wind(bft)": "O 3",
        "Wind(m/s)": "4.99",
        "Windstoot(km/uur)": "34",
        "Zicht(m)": "45000",
        "Druk(hPa)": "1024.5"
    }
]
