[
    {
        "timestamp": "2025-04-02T05:30:00.000Z",
        "Station": "Lauwersoog",
        "Weer": "",
        "Temp(\u00b0C)": "6.9",
        "RV(%)": "69",
        "Wind(bft)": "O 3",
        "Wind(m/s)": "5.07",
        "Windstoot(km/uur)": "24",
        "Zicht(m)": "",
        "Druk(hPa)": ""
    },
    {
        "timestamp": "2025-04-02T05:30:00.000Z",
        "Station": "Nieuw Beerta",
        "Weer": "",
        "Temp(\u00b0C)": "2.3",
        "RV(%)": "88",
        "Wind(bft)": "ONO 3",
        "Wind(m/s)": "4.9",
        "Windstoot(km/uur)": "20",
        "Zicht(m)": "",
        "Druk(hPa)": ""
    },
    {
        "timestamp": "2025-04-02T05:30:00.000Z",
        "Station": "Terschelling",
        "Weer": "",
        "Temp(\u00b0C)": "5.7",
        "RV(%)": "87",
        "Wind(bft)": "ONO 4",
        "Wind(m/s)": "5.96",
        "Windstoot(km/uur)": "26",
        "Zicht(m)": "28000",
        "Druk(hPa)": "1028.7"
    },
    {
        "timestamp": "2025-04-02T05:30:00.000Z",
        "Station": "Vlieland",
        "Weer": "onbewolkt",
        "Temp(\u00b0C)": "7.4",
        "RV(%)": "75",
        "Wind(bft)": "O 4",
        "Wind(m/s)": "6.99",
        "Windstoot(km/uur)": "32",
        "Zicht(m)": "45000",
        "Druk(hPa)": "1028.1"
    },
    {
        "timestamp": "2025-04-02T05:30:00.000Z",
        "Station": "Leeuwarden",
        "Weer": "onbewolkt",
        "Temp(\u00b0C)": "3.4",
        "RV(%)": "81",
        "Wind(bft)": "ONO 3",
        "Wind(m/s)": "4.06",
        "Windstoot(km/uur)": "17",
        "Zicht(m)": "45000",
        "Druk(hPa)": "1028.6"
    },
    {
        "timestamp": "2025-04-02T05:30:00.000Z",
        "Station": "Stavoren",
        "Weer": "onbewolkt",
        "Temp(\u00b0C)": "5.1",
        "RV(%)": "78",
        "Wind(bft)": "ONO 3",
        "Wind(m/s)": "4.22",
        "Windstoot(km/uur)": "23",
        "Zicht(m)": "45000",
        "Druk(hPa)": ""
    },
    {
        "timestamp": "2025-04-02T05:30:00.000Z",
        "Station": "Houtribdijk",
        "Weer": "",
        "Temp(\u00b0C)": "",
        "RV(%)": "",
        "Wind(bft)": "O 5",
        "Wind(m/s)": "9.98",
        "Windstoot(km/uur)": "42",
        "Zicht(m)": "",
        "Druk(hPa)": ""
    },
    {
        "timestamp": "2025-04-02T05:30:00.000Z",
        "Station": "Eelde",
        "Weer": "onbewolkt",
        "Temp(\u00b0C)": "2.8",
        "RV(%)": "84",
        "Wind(bft)": "ONO 2",
        "Wind(m/s)": "2.7",
        "Windstoot(km/uur)": "14",
        "Zicht(m)": "45000",
        "Druk(hPa)": "1028.7"
    },
    {
        "timestamp": "2025-04-02T05:30:00.000Z",
        "Station": "Hoogeveen",
        "Weer": "onbewolkt",
        "Temp(\u00b0C)": "2.3",
        "RV(%)": "85",
        "Wind(bft)": "NO 2",
        "Wind(m/s)": "3.32",
        "Windstoot(km/uur)": "14",
        "Zicht(m)": "50000",
        "Druk(hPa)": "1027.9"
    },
    {
        "timestamp": "2025-04-02T05:30:00.000Z",
        "Station": "Heino",
        "Weer": "",
        "Temp(\u00b0C)": "4.9",
        "RV(%)": "76",
        "Wind(bft)": "NO 2",
        "Wind(m/s)": "3.3",
        "Windstoot(km/uur)": "18",
        "Zicht(m)": "",
        "Druk(hPa)": ""
    },
    {
        "timestamp": "2025-04-02T05:30:00.000Z",
        "Station": "Twenthe",
        "Weer": "onbewolkt",
        "Temp(\u00b0C)": "4.7",
        "RV(%)": "77",
        "Wind(bft)": "NO 2",
        "Wind(m/s)": "3.23",
        "Windstoot(km/uur)": "18",
        "Zicht(m)": "45000",
        "Druk(hPa)": "1027.1"
    },
    {
        "timestamp": "2025-04-02T05:30:00.000Z",
        "Station": "Deelen",
        "Weer": "onbewolkt",
        "Temp(\u00b0C)": "5.4",
        "RV(%)": "75",
        "Wind(bft)": "NO 3",
        "Wind(m/s)": "4.78",
        "Windstoot(km/uur)": "24",
        "Zicht(m)": "45000",
        "Druk(hPa)": "1026.3"
    },
    {
        "timestamp": "2025-04-02T05:30:00.000Z",
        "Station": "Hupsel",
        "Weer": "",
        "Temp(\u00b0C)": "5.7",
        "RV(%)": "75",
        "Wind(bft)": "NO 3",
        "Wind(m/s)": "3.56",
        "Windstoot(km/uur)": "20",
        "Zicht(m)": "",
        "Druk(hPa)": ""
    },
    {
        "timestamp": "2025-04-02T05:30:00.000Z",
        "Station": "Herwijnen",
        "Weer": "",
        "Temp(\u00b0C)": "6.1",
        "RV(%)": "71",
        "Wind(bft)": "ONO 3",
        "Wind(m/s)": "4.74",
        "Windstoot(km/uur)": "23",
        "Zicht(m)": "",
        "Druk(hPa)": "1025.5"
    },
    {
        "timestamp": "2025-04-02T05:30:00.000Z",
        "Station": "Marknesse",
        "Weer": "",
        "Temp(\u00b0C)": "3.7",
        "RV(%)": "83",
        "Wind(bft)": "ONO 2",
        "Wind(m/s)": "3.25",
        "Windstoot(km/uur)": "16",
        "Zicht(m)": "50000",
        "Druk(hPa)": ""
    },
    {
        "timestamp": "2025-04-02T05:30:00.000Z",
        "Station": "Lelystad",
        "Weer": "onbewolkt",
        "Temp(\u00b0C)": "3.7",
        "RV(%)": "84",
        "Wind(bft)": "ONO 3",
        "Wind(m/s)": "3.85",
        "Windstoot(km/uur)": "17",
        "Zicht(m)": "45000",
        "Druk(hPa)": "1027.0"
    },
    {
        "timestamp": "2025-04-02T05:30:00.000Z",
        "Station": "De Bilt",
        "Weer": "onbewolkt",
        "Temp(\u00b0C)": "6.4",
        "RV(%)": "70",
        "Wind(bft)": "ONO 3",
        "Wind(m/s)": "4.26",
        "Windstoot(km/uur)": "25",
        "Zicht(m)": "45000",
        "Druk(hPa)": "1026.0"
    },
    {
        "timestamp": "2025-04-02T05:30:00.000Z",
        "Station": "Cabauw",
        "Weer": "",
        "Temp(\u00b0C)": "7.1",
        "RV(%)": "68",
        "Wind(bft)": "ONO 3",
        "Wind(m/s)": "4.97",
        "Windstoot(km/uur)": "29",
        "Zicht(m)": "45000",
        "Druk(hPa)": "1025.7"
    },
    {
        "timestamp": "2025-04-02T05:30:00.000Z",
        "Station": "Den Helder",
        "Weer": "onbewolkt",
        "Temp(\u00b0C)": "7.4",
        "RV(%)": "77",
        "Wind(bft)": "O 3",
        "Wind(m/s)": "5.28",
        "Windstoot(km/uur)": "26",
        "Zicht(m)": "45000",
        "Druk(hPa)": "1027.5"
    },
    {
        "timestamp": "2025-04-02T05:30:00.000Z",
        "Station": "Texelhors",
        "Weer": "",
        "Temp(\u00b0C)": "",
        "RV(%)": "",
        "Wind(bft)": "ONO 3",
        "Wind(m/s)": "5.19",
        "Windstoot(km/uur)": "24",
        "Zicht(m)": "",
        "Druk(hPa)": ""
    },
    {
        "timestamp": "2025-04-02T05:30:00.000Z",
        "Station": "Berkhout",
        "Weer": "",
        "Temp(\u00b0C)": "5.3",
        "RV(%)": "83",
        "Wind(bft)": "ONO 3",
        "Wind(m/s)": "4.99",
        "Windstoot(km/uur)": "22",
        "Zicht(m)": "31000",
        "Druk(hPa)": ""
    },
    {
        "timestamp": "2025-04-02T05:30:00.000Z",
        "Station": "IJmuiden",
        "Weer": "",
        "Temp(\u00b0C)": "",
        "RV(%)": "",
        "Wind(bft)": "ONO 4",
        "Wind(m/s)": "6.74",
        "Windstoot(km/uur)": "30",
        "Zicht(m)": "",
        "Druk(hPa)": ""
    },
    {
        "timestamp": "2025-04-02T05:30:00.000Z",
        "Station": "Wijk aan Zee",
        "Weer": "",
        "Temp(\u00b0C)": "5.4",
        "RV(%)": "86",
        "Wind(bft)": "",
        "Wind(m/s)": "",
        "Windstoot(km/uur)": "",
        "Zicht(m)": "",
        "Druk(hPa)": ""
    },
    {
        "timestamp": "2025-04-02T05:30:00.000Z",
        "Station": "Schiphol",
        "Weer": "onbewolkt",
        "Temp(\u00b0C)": "6.9",
        "RV(%)": "74",
        "Wind(bft)": "ONO 3",
        "Wind(m/s)": "4.2",
        "Windstoot(km/uur)": "23",
        "Zicht(m)": "45000",
        "Druk(hPa)": "1026.4"
    },
    {
        "timestamp": "2025-04-02T05:30:00.000Z",
        "Station": "Voorschoten",
        "Weer": "onbewolkt",
        "Temp(\u00b0C)": "7.7",
        "RV(%)": "68",
        "Wind(bft)": "ONO 3",
        "Wind(m/s)": "5.3",
        "Windstoot(km/uur)": "30",
        "Zicht(m)": "45000",
        "Druk(hPa)": "1026.0"
    },
    {
        "timestamp": "2025-04-02T05:30:00.000Z",
        "Station": "Rotterdam",
        "Weer": "onbewolkt",
        "Temp(\u00b0C)": "5.2",
        "RV(%)": "76",
        "Wind(bft)": "ONO 3",
        "Wind(m/s)": "3.73",
        "Windstoot(km/uur)": "17",
        "Zicht(m)": "45000",
        "Druk(hPa)": "1025.7"
    },
    {
        "timestamp": "2025-04-02T05:30:00.000Z",
        "Station": "Hoek van Holland",
        "Weer": "",
        "Temp(\u00b0C)": "7.3",
        "RV(%)": "67",
        "Wind(bft)": "ONO 4",
        "Wind(m/s)": "6.6",
        "Windstoot(km/uur)": "30",
        "Zicht(m)": "",
        "Druk(hPa)": "1025.5"
    },
    {
        "timestamp": "2025-04-02T05:30:00.000Z",
        "Station": "Wilhelminadorp",
        "Weer": "",
        "Temp(\u00b0C)": "7.5",
        "RV(%)": "67",
        "Wind(bft)": "ONO 4",
        "Wind(m/s)": "5.65",
        "Windstoot(km/uur)": "29",
        "Zicht(m)": "",
        "Druk(hPa)": "1024.2"
    },
    {
        "timestamp": "2025-04-02T05:30:00.000Z",
        "Station": "Vlissingen",
        "Weer": "onbewolkt",
        "Temp(\u00b0C)": "8.2",
        "RV(%)": "65",
        "Wind(bft)": "NO 4",
        "Wind(m/s)": "6.57",
        "Windstoot(km/uur)": "35",
        "Zicht(m)": "45000",
        "Druk(hPa)": "1023.8"
    },
    {
        "timestamp": "2025-04-02T05:30:00.000Z",
        "Station": "Westdorpe",
        "Weer": "",
        "Temp(\u00b0C)": "6.4",
        "RV(%)": "69",
        "Wind(bft)": "ONO 3",
        "Wind(m/s)": "4.31",
        "Windstoot(km/uur)": "24",
        "Zicht(m)": "50000",
        "Druk(hPa)": "1023.7"
    },
    {
        "timestamp": "2025-04-02T05:30:00.000Z",
        "Station": "Woensdrecht",
        "Weer": "onbewolkt",
        "Temp(\u00b0C)": "4.9",
        "RV(%)": "75",
        "Wind(bft)": "ONO 3",
        "Wind(m/s)": "4.22",
        "Windstoot(km/uur)": "20",
        "Zicht(m)": "45000",
        "Druk(hPa)": "1024.2"
    },
    {
        "timestamp": "2025-04-02T05:30:00.000Z",
        "Station": "Gilze Rijen",
        "Weer": "onbewolkt",
        "Temp(\u00b0C)": "6.9",
        "RV(%)": "65",
        "Wind(bft)": "ONO 3",
        "Wind(m/s)": "5.28",
        "Windstoot(km/uur)": "27",
        "Zicht(m)": "45000",
        "Druk(hPa)": "1024.8"
    },
    {
        "timestamp": "2025-04-02T05:30:00.000Z",
        "Station": "Volkel",
        "Weer": "onbewolkt",
        "Temp(\u00b0C)": "5.8",
        "RV(%)": "73",
        "Wind(bft)": "NO 2",
        "Wind(m/s)": "3.23",
        "Windstoot(km/uur)": "18",
        "Zicht(m)": "45000",
        "Druk(hPa)": "1025.2"
    },
    {
        "timestamp": "2025-04-02T05:30:00.000Z",
        "Station": "Eindhoven",
        "Weer": "onbewolkt",
        "Temp(\u00b0C)": "6.5",
        "RV(%)": "70",
        "Wind(bft)": "NO 3",
        "Wind(m/s)": "4.39",
        "Windstoot(km/uur)": "23",
        "Zicht(m)": "45000",
        "Druk(hPa)": "1024.7"
    },
    {
        "timestamp": "2025-04-02T05:30:00.000Z",
        "Station": "Ell",
        "Weer": "onbewolkt",
        "Temp(\u00b0C)": "6",
        "RV(%)": "73",
        "Wind(bft)": "NO 3",
        "Wind(m/s)": "4.33",
        "Windstoot(km/uur)": "21",
        "Zicht(m)": "50000",
        "Druk(hPa)": ""
    },
    {
        "timestamp": "2025-04-02T05:30:00.000Z",
        "Station": "Arcen",
        "Weer": "",
        "Temp(\u00b0C)": "6.6",
        "RV(%)": "67",
        "Wind(bft)": "NO 3",
        "Wind(m/s)": "3.52",
        "Windstoot(km/uur)": "23",
        "Zicht(m)": "",
        "Druk(hPa)": ""
    },
    {
        "timestamp": "2025-04-02T05:30:00.000Z",
        "Station": "Maastricht-Aachen Airport",
        "Weer": "licht bewolkt",
        "Temp(\u00b0C)": "5.5",
        "RV(%)": "71",
        "Wind(bft)": "NO 3",
        "Wind(m/s)": "4.99",
        "Windstoot(km/uur)": "23",
        "Zicht(m)": "45000",
        "Druk(hPa)": "1023.3"
    }
]
